macq/__init__.py
macq/extract/__init__.py
macq/extract/amdn.py
macq/extract/arms.py
macq/extract/exceptions.py
macq/extract/extract.py
macq/extract/learned_action.py
macq/extract/learned_fluent.py
macq/extract/locm.py
macq/extract/model.py
macq/extract/observer.py
macq/extract/slaf.py
macq/generate/__init__.py
macq/generate/csv.py
macq/generate/plan.py
macq/generate/pddl/__init__.py
macq/generate/pddl/fd_random_walk.py
macq/generate/pddl/generator.py
macq/generate/pddl/planning_domains_api.py
macq/generate/pddl/random_goal_sampling.py
macq/generate/pddl/trace_from_goal.py
macq/generate/pddl/vanilla_sampling.py
macq/observation/__init__.py
macq/observation/action_observation.py
macq/observation/atomic_partial_observation.py
macq/observation/id_observation.py
macq/observation/identity_observation.py
macq/observation/noisy_observation.py
macq/observation/noisy_partial_disordered_parallel_observation.py
macq/observation/noisy_partial_observation.py
macq/observation/observation.py
macq/observation/observed_tracelist.py
macq/observation/partial_observation.py
macq/trace/__init__.py
macq/trace/action.py
macq/trace/disordered_parallel_actions_observation_lists.py
macq/trace/fluent.py
macq/trace/partial_state.py
macq/trace/state.py
macq/trace/step.py
macq/trace/trace.py
macq/trace/trace_list.py
macq/utils/__init__.py
macq/utils/common_errors.py
macq/utils/complex_encoder.py
macq/utils/progress.py
macq/utils/pysat.py
macq/utils/timer.py
macq/utils/tokenization_errors.py
macq/utils/tokenization_utils.py
macq/utils/trace_errors.py
macq/utils/trace_utils.py
macq-0.3.11.dist-info/LICENSE
macq-0.3.11.dist-info/METADATA
macq-0.3.11.dist-info/WHEEL
macq-0.3.11.dist-info/top_level.txt
macq-0.3.11.dist-info/RECORD
