Metadata-Version: 2.1
Name: macq
Version: 0.3.11
Summary: Action model acquisition from state trace data.
Author: Ethan Callanan, Rebecca De Venezia, Victoria Armstrong, Alison Parades, Tathagata Chakraborti
Author-email: Christian Muise <christian.muise@queensu.ca>
Maintainer-email: Christian Muise <christian.muise@queensu.ca>
License: MIT License
Project-URL: Homepage, https://macq.planning.domains
Project-URL: Documentation, https://ai-planning.github.io/macq/
Project-URL: Repository, https://github.com/ai-planning/macq
Keywords: planning,action model acquisition
Classifier: Intended Audience :: Science/Research
Classifier: Topic :: Scientific/Engineering
Classifier: Topic :: Scientific/Engineering :: Mathematics
Classifier: Programming Language :: Python
Classifier: Programming Language :: Python :: 3
Classifier: Programming Language :: Python :: 3.9
Classifier: Programming Language :: Python :: 3.10
Classifier: Programming Language :: Python :: 3.11
Classifier: Programming Language :: Python :: 3.12
Classifier: Programming Language :: Python :: 3 :: Only
Classifier: License :: OSI Approved :: MIT License
Classifier: Operating System :: OS Independent
Requires-Python: >=3.8
License-File: LICENSE
Requires-Dist: tarski
Requires-Dist: requests
Requires-Dist: rich
Requires-Dist: nnf
Requires-Dist: python-sat
Requires-Dist: bauhaus
Requires-Dist: numpy
Requires-Dist: clingo
Requires-Dist: graphviz
Requires-Dist: networkx
Requires-Dist: pydot
Provides-Extra: dev
Requires-Dist: pytest; extra == "dev"
Requires-Dist: pytest-cov; extra == "dev"
Requires-Dist: flake8; extra == "dev"
Requires-Dist: black; extra == "dev"
Requires-Dist: pre-commit; extra == "dev"
